{"optimized_hyperparameter_config": {"CreateDataLoader:batch_size": 263, "Imputation:strategy": "most_frequent", "InitializationSelector:initialization_method": "sparse", "InitializationSelector:initializer:initialize_bias": "Yes", "LearningrateSchedulerSelector:lr_scheduler": "cosine_annealing", "LossModuleSelector:loss_module": "cross_entropy", "NetworkSelector:network": "shapedresnet", "NormalizationStrategySelector:normalization_strategy": "none", "OptimizerSelector:optimizer": "adam", "PreprocessorSelector:preprocessor": "truncated_svd", "ResamplingStrategySelector:over_sampling_method": "smote", "ResamplingStrategySelector:target_size_strategy": "none", "ResamplingStrategySelector:under_sampling_method": "random", "TrainNode:batch_loss_computation_technique": "mixup", "InitializationSelector:sparse:sparsity": 0.9, "LearningrateSchedulerSelector:cosine_annealing:T_max": 435, "LearningrateSchedulerSelector:cosine_annealing:eta_min": 1e-08, "NetworkSelector:shapedresnet:activation": "relu", "NetworkSelector:shapedresnet:blocks_per_group": 4, "NetworkSelector:shapedresnet:max_units": 35, "NetworkSelector:shapedresnet:num_groups": 3, "NetworkSelector:shapedresnet:resnet_shape": "brick", "NetworkSelector:shapedresnet:use_dropout": true, "NetworkSelector:shapedresnet:use_shake_drop": true, "NetworkSelector:shapedresnet:use_shake_shake": false, "OptimizerSelector:adam:learning_rate": 0.004589677150068039, "OptimizerSelector:adam:weight_decay": 0.02444516103724879, "PreprocessorSelector:truncated_svd:target_dim": 16, "ResamplingStrategySelector:smote:k_neighbors": 3, "TrainNode:mixup:alpha": 0.04305436852822542, "NetworkSelector:shapedresnet:max_dropout": 0.5479630880206022, "NetworkSelector:shapedresnet:max_shake_drop_probability": 0.6388125514458807}, "budget": 30.0, "loss": -55.434782608695656, "info": {"loss": 0.8605815172195435, "model_parameters": 32693.0, "train_accuracy": 37.6425855513308, "lr_scheduler_converged": 0.0, "lr": 0.000979830757867546, "val_accuracy": 55.434782608695656}}